clampsuite/__init__.py
clampsuite/__main__.py
clampsuite/py.typed
clampsuite/acq/__init__.py
clampsuite/acq/acquisition.py
clampsuite/acq/current_clamp_acq.py
clampsuite/acq/filter_acq.py
clampsuite/acq/lfp_acq.py
clampsuite/acq/mini_acq.py
clampsuite/acq/oepsc_acq.py
clampsuite/acq/postsynaptic_event.py
clampsuite/final_analysis/__init__.py
clampsuite/final_analysis/final_analysis.py
clampsuite/final_analysis/final_current_clamp.py
clampsuite/final_analysis/final_evoked.py
clampsuite/final_analysis/final_mini_analysis.py
clampsuite/functions/__init__.py
clampsuite/functions/curve_fit.py
clampsuite/functions/filtering_functions.py
clampsuite/functions/kde.py
clampsuite/functions/load_functions.py
clampsuite/functions/startup.py
clampsuite/functions/template_psc.py
clampsuite/functions/utilities.py
clampsuite/gui_main/__init__.py
clampsuite/gui_main/acq_inspection.py
clampsuite/gui_main/current_clamp_widget.py
clampsuite/gui_main/filter_widget.py
clampsuite/gui_main/main_window.py
clampsuite/gui_main/mini_analysis_widget.py
clampsuite/gui_main/oepsc_widget.py
clampsuite/gui_main/pref_widget.py
clampsuite/gui_widgets/__init__.py
clampsuite/gui_widgets/qtwidgets.py
clampsuite/logo/d_logo.png
clampsuite/manager/__init__.py
clampsuite/manager/exp_manager.py
clampsuite-0.0.4.dist-info/LICENSE
clampsuite-0.0.4.dist-info/METADATA
clampsuite-0.0.4.dist-info/WHEEL
clampsuite-0.0.4.dist-info/entry_points.txt
clampsuite-0.0.4.dist-info/top_level.txt
clampsuite-0.0.4.dist-info/RECORD
