Metadata-Version: 2.1
Name: clampsuite
Version: 0.0.4
Summary: Slice electrophysiology analysis package for analyzing mEPSCs, o/eEPSCs and current clamp data.
Author-email: Lars Henrik Nelson <larshnelson@protonmail.com>
License: GNU GENERAL PUBLIC LICENSE
Project-URL: Homepage, https://github.com/LarsHenrikNelson/ClampSuite
Project-URL: Documentation, https://clampsuite.readthedocs.io/
Keywords: electrophysiology,analysis
Requires-Python: >=3.9
License-File: LICENSE
Requires-Dist: Bottleneck >=1.3.5
Requires-Dist: KDEpy
Requires-Dist: numpy >=1.23.3
Requires-Dist: openpyxl >=3.0.10
Requires-Dist: pandas >=1.4.4
Requires-Dist: PyQt5 >=5.15.7
Requires-Dist: pyqtgraph >=0.13.1
Requires-Dist: pyyaml >=6.0
Requires-Dist: qdarkstyle >=3.0
Requires-Dist: scipy >=1.9.1
Requires-Dist: xlsxwriter >=3.0.3
Provides-Extra: data
Requires-Dist: h5py ; extra == 'data'
Provides-Extra: plotting
Requires-Dist: matplotlib ; extra == 'plotting'
Provides-Extra: testing
Requires-Dist: pytest >=6.0 ; extra == 'testing'
Requires-Dist: pytest-cov ; extra == 'testing'
Requires-Dist: ruff ; extra == 'testing'
Requires-Dist: mypy ; extra == 'testing'
Requires-Dist: tox ; extra == 'testing'
